topsis/__init__.py
topsis/topsis.py
topsis_jatin_102203713-0.2.1.dist-info/LICENSE
topsis_jatin_102203713-0.2.1.dist-info/METADATA
topsis_jatin_102203713-0.2.1.dist-info/WHEEL
topsis_jatin_102203713-0.2.1.dist-info/entry_points.txt
topsis_jatin_102203713-0.2.1.dist-info/top_level.txt
topsis_jatin_102203713-0.2.1.dist-info/RECORD
