Metadata-Version: 2.1
Name: topsis_jatin_102203713
Version: 0.2.1
Summary: Technique for Order Preference by Similarity to Ideal Solution(TOPSIS) Package
Author: Jatin Bagga
Author-email: aloc1345@gmail.com
Keywords: python,topsis,multi-criteria decision-making,mcdm,ranking
Classifier: Programming Language :: Python :: 3
Classifier: License :: OSI Approved :: MIT License
Classifier: Operating System :: OS Independent
Requires-Python: >=3.6
License-File: LICENSE
Requires-Dist: numpy
Requires-Dist: pandas
Requires-Dist: openpyxl
